<annotation>
	<folder>&#26631;&#27880;&#20869;&#23481;</folder>
	<filename>K387+111_K387+141_2.jpg</filename>
	<path>./enhance_xml/K387+111_K387+141_2.jpg</path>
	<source>
		<database>Unknown</database>
	</source>
	<size>
		<width>1628</width>
		<height>635</height>
		<depth>1</depth>
	</size>
	<segmented>0</segmented>
	<object>
		<name>light</name>
		<pose>Unspecified</pose>
		<truncated>0</truncated>
		<difficult>0</difficult>
		<bndbox>
			<xmin>1504</xmin>
			<ymin>205</ymin>
			<xmax>1539</xmax>
			<ymax>217</ymax>
		</bndbox>
	</object>
	<object>
		<name>light</name>
		<pose>Unspecified</pose>
		<truncated>0</truncated>
		<difficult>0</difficult>
		<bndbox>
			<xmin>1471</xmin>
			<ymin>205</ymin>
			<xmax>1506</xmax>
			<ymax>217</ymax>
		</bndbox>
	</object>
	<object>
		<name>light</name>
		<pose>Unspecified</pose>
		<truncated>0</truncated>
		<difficult>0</difficult>
		<bndbox>
			<xmin>1431</xmin>
			<ymin>205</ymin>
			<xmax>1466</xmax>
			<ymax>217</ymax>
		</bndbox>
	</object>
	<object>
		<name>light</name>
		<pose>Unspecified</pose>
		<truncated>0</truncated>
		<difficult>0</difficult>
		<bndbox>
			<xmin>1394</xmin>
			<ymin>204</ymin>
			<xmax>1429</xmax>
			<ymax>219</ymax>
		</bndbox>
	</object>
	<object>
		<name>light</name>
		<pose>Unspecified</pose>
		<truncated>0</truncated>
		<difficult>0</difficult>
		<bndbox>
			<xmin>1320</xmin>
			<ymin>203</ymin>
			<xmax>1356</xmax>
			<ymax>217</ymax>
		</bndbox>
	</object>
	<object>
		<name>light</name>
		<pose>Unspecified</pose>
		<truncated>0</truncated>
		<difficult>0</difficult>
		<bndbox>
			<xmin>1364</xmin>
			<ymin>204</ymin>
			<xmax>1388</xmax>
			<ymax>211</ymax>
		</bndbox>
	</object>
	<object>
		<name>light</name>
		<pose>Unspecified</pose>
		<truncated>0</truncated>
		<difficult>0</difficult>
		<bndbox>
			<xmin>1284</xmin>
			<ymin>202</ymin>
			<xmax>1320</xmax>
			<ymax>216</ymax>
		</bndbox>
	</object>
	<object>
		<name>light</name>
		<pose>Unspecified</pose>
		<truncated>0</truncated>
		<difficult>0</difficult>
		<bndbox>
			<xmin>1249</xmin>
			<ymin>202</ymin>
			<xmax>1284</xmax>
			<ymax>217</ymax>
		</bndbox>
	</object>
	<object>
		<name>light</name>
		<pose>Unspecified</pose>
		<truncated>0</truncated>
		<difficult>0</difficult>
		<bndbox>
			<xmin>1214</xmin>
			<ymin>205</ymin>
			<xmax>1249</xmax>
			<ymax>217</ymax>
		</bndbox>
	</object>
	<object>
		<name>light</name>
		<pose>Unspecified</pose>
		<truncated>0</truncated>
		<difficult>0</difficult>
		<bndbox>
			<xmin>1179</xmin>
			<ymin>204</ymin>
			<xmax>1213</xmax>
			<ymax>217</ymax>
		</bndbox>
	</object>
	<object>
		<name>light</name>
		<pose>Unspecified</pose>
		<truncated>0</truncated>
		<difficult>0</difficult>
		<bndbox>
			<xmin>1143</xmin>
			<ymin>202</ymin>
			<xmax>1178</xmax>
			<ymax>219</ymax>
		</bndbox>
	</object>
	<object>
		<name>light</name>
		<pose>Unspecified</pose>
		<truncated>0</truncated>
		<difficult>0</difficult>
		<bndbox>
			<xmin>1105</xmin>
			<ymin>202</ymin>
			<xmax>1140</xmax>
			<ymax>219</ymax>
		</bndbox>
	</object>
	<object>
		<name>light</name>
		<pose>Unspecified</pose>
		<truncated>0</truncated>
		<difficult>0</difficult>
		<bndbox>
			<xmin>1055</xmin>
			<ymin>202</ymin>
			<xmax>1097</xmax>
			<ymax>219</ymax>
		</bndbox>
	</object>
	<object>
		<name>light</name>
		<pose>Unspecified</pose>
		<truncated>0</truncated>
		<difficult>0</difficult>
		<bndbox>
			<xmin>1021</xmin>
			<ymin>202</ymin>
			<xmax>1054</xmax>
			<ymax>217</ymax>
		</bndbox>
	</object>
	<object>
		<name>light</name>
		<pose>Unspecified</pose>
		<truncated>0</truncated>
		<difficult>0</difficult>
		<bndbox>
			<xmin>982</xmin>
			<ymin>202</ymin>
			<xmax>1016</xmax>
			<ymax>218</ymax>
		</bndbox>
	</object>
	<object>
		<name>light</name>
		<pose>Unspecified</pose>
		<truncated>0</truncated>
		<difficult>0</difficult>
		<bndbox>
			<xmin>947</xmin>
			<ymin>203</ymin>
			<xmax>979</xmax>
			<ymax>217</ymax>
		</bndbox>
	</object>
	<object>
		<name>light</name>
		<pose>Unspecified</pose>
		<truncated>0</truncated>
		<difficult>0</difficult>
		<bndbox>
			<xmin>908</xmin>
			<ymin>202</ymin>
			<xmax>943</xmax>
			<ymax>217</ymax>
		</bndbox>
	</object>
	<object>
		<name>light</name>
		<pose>Unspecified</pose>
		<truncated>0</truncated>
		<difficult>0</difficult>
		<bndbox>
			<xmin>874</xmin>
			<ymin>203</ymin>
			<xmax>908</xmax>
			<ymax>218</ymax>
		</bndbox>
	</object>
	<object>
		<name>light</name>
		<pose>Unspecified</pose>
		<truncated>0</truncated>
		<difficult>0</difficult>
		<bndbox>
			<xmin>836</xmin>
			<ymin>202</ymin>
			<xmax>871</xmax>
			<ymax>219</ymax>
		</bndbox>
	</object>
	<object>
		<name>light</name>
		<pose>Unspecified</pose>
		<truncated>0</truncated>
		<difficult>0</difficult>
		<bndbox>
			<xmin>804</xmin>
			<ymin>206</ymin>
			<xmax>826</xmax>
			<ymax>214</ymax>
		</bndbox>
	</object>
	<object>
		<name>light</name>
		<pose>Unspecified</pose>
		<truncated>0</truncated>
		<difficult>0</difficult>
		<bndbox>
			<xmin>764</xmin>
			<ymin>204</ymin>
			<xmax>797</xmax>
			<ymax>217</ymax>
		</bndbox>
	</object>
	<object>
		<name>light</name>
		<pose>Unspecified</pose>
		<truncated>0</truncated>
		<difficult>0</difficult>
		<bndbox>
			<xmin>727</xmin>
			<ymin>204</ymin>
			<xmax>760</xmax>
			<ymax>217</ymax>
		</bndbox>
	</object>
	<object>
		<name>light</name>
		<pose>Unspecified</pose>
		<truncated>0</truncated>
		<difficult>0</difficult>
		<bndbox>
			<xmin>688</xmin>
			<ymin>204</ymin>
			<xmax>721</xmax>
			<ymax>218</ymax>
		</bndbox>
	</object>
	<object>
		<name>light</name>
		<pose>Unspecified</pose>
		<truncated>0</truncated>
		<difficult>0</difficult>
		<bndbox>
			<xmin>651</xmin>
			<ymin>204</ymin>
			<xmax>683</xmax>
			<ymax>217</ymax>
		</bndbox>
	</object>
	<object>
		<name>light</name>
		<pose>Unspecified</pose>
		<truncated>0</truncated>
		<difficult>0</difficult>
		<bndbox>
			<xmin>613</xmin>
			<ymin>205</ymin>
			<xmax>646</xmax>
			<ymax>217</ymax>
		</bndbox>
	</object>
	<object>
		<name>light</name>
		<pose>Unspecified</pose>
		<truncated>0</truncated>
		<difficult>0</difficult>
		<bndbox>
			<xmin>577</xmin>
			<ymin>205</ymin>
			<xmax>610</xmax>
			<ymax>219</ymax>
		</bndbox>
	</object>
	<object>
		<name>light</name>
		<pose>Unspecified</pose>
		<truncated>0</truncated>
		<difficult>0</difficult>
		<bndbox>
			<xmin>540</xmin>
			<ymin>204</ymin>
			<xmax>573</xmax>
			<ymax>218</ymax>
		</bndbox>
	</object>
	<object>
		<name>light</name>
		<pose>Unspecified</pose>
		<truncated>0</truncated>
		<difficult>0</difficult>
		<bndbox>
			<xmin>498</xmin>
			<ymin>203</ymin>
			<xmax>539</xmax>
			<ymax>219</ymax>
		</bndbox>
	</object>
	<object>
		<name>light</name>
		<pose>Unspecified</pose>
		<truncated>0</truncated>
		<difficult>0</difficult>
		<bndbox>
			<xmin>463</xmin>
			<ymin>205</ymin>
			<xmax>500</xmax>
			<ymax>219</ymax>
		</bndbox>
	</object>
	<object>
		<name>light</name>
		<pose>Unspecified</pose>
		<truncated>0</truncated>
		<difficult>0</difficult>
		<bndbox>
			<xmin>425</xmin>
			<ymin>205</ymin>
			<xmax>462</xmax>
			<ymax>219</ymax>
		</bndbox>
	</object>
	<object>
		<name>light</name>
		<pose>Unspecified</pose>
		<truncated>0</truncated>
		<difficult>0</difficult>
		<bndbox>
			<xmin>387</xmin>
			<ymin>205</ymin>
			<xmax>422</xmax>
			<ymax>219</ymax>
		</bndbox>
	</object>
	<object>
		<name>light</name>
		<pose>Unspecified</pose>
		<truncated>0</truncated>
		<difficult>0</difficult>
		<bndbox>
			<xmin>349</xmin>
			<ymin>205</ymin>
			<xmax>384</xmax>
			<ymax>219</ymax>
		</bndbox>
	</object>
	<object>
		<name>light</name>
		<pose>Unspecified</pose>
		<truncated>0</truncated>
		<difficult>0</difficult>
		<bndbox>
			<xmin>312</xmin>
			<ymin>205</ymin>
			<xmax>347</xmax>
			<ymax>219</ymax>
		</bndbox>
	</object>
	<object>
		<name>light</name>
		<pose>Unspecified</pose>
		<truncated>0</truncated>
		<difficult>0</difficult>
		<bndbox>
			<xmin>274</xmin>
			<ymin>205</ymin>
			<xmax>309</xmax>
			<ymax>219</ymax>
		</bndbox>
	</object>
	<object>
		<name>light</name>
		<pose>Unspecified</pose>
		<truncated>0</truncated>
		<difficult>0</difficult>
		<bndbox>
			<xmin>196</xmin>
			<ymin>204</ymin>
			<xmax>233</xmax>
			<ymax>218</ymax>
		</bndbox>
	</object>
	<object>
		<name>light</name>
		<pose>Unspecified</pose>
		<truncated>0</truncated>
		<difficult>0</difficult>
		<bndbox>
			<xmin>240</xmin>
			<ymin>206</ymin>
			<xmax>263</xmax>
			<ymax>216</ymax>
		</bndbox>
	</object>
	<object>
		<name>light</name>
		<pose>Unspecified</pose>
		<truncated>0</truncated>
		<difficult>0</difficult>
		<bndbox>
			<xmin>160</xmin>
			<ymin>206</ymin>
			<xmax>193</xmax>
			<ymax>219</ymax>
		</bndbox>
	</object>
	<object>
		<name>light</name>
		<pose>Unspecified</pose>
		<truncated>0</truncated>
		<difficult>0</difficult>
		<bndbox>
			<xmin>123</xmin>
			<ymin>204</ymin>
			<xmax>155</xmax>
			<ymax>220</ymax>
		</bndbox>
	</object>
	<object>
		<name>light</name>
		<pose>Unspecified</pose>
		<truncated>1</truncated>
		<difficult>0</difficult>
		<bndbox>
			<xmin>1507</xmin>
			<ymin>420</ymin>
			<xmax>1542</xmax>
			<ymax>437</ymax>
		</bndbox>
	</object>
	<object>
		<name>light</name>
		<pose>Unspecified</pose>
		<truncated>0</truncated>
		<difficult>0</difficult>
		<bndbox>
			<xmin>1472</xmin>
			<ymin>421</ymin>
			<xmax>1509</xmax>
			<ymax>434</ymax>
		</bndbox>
	</object>
	<object>
		<name>light</name>
		<pose>Unspecified</pose>
		<truncated>0</truncated>
		<difficult>0</difficult>
		<bndbox>
			<xmin>1436</xmin>
			<ymin>422</ymin>
			<xmax>1472</xmax>
			<ymax>434</ymax>
		</bndbox>
	</object>
	<object>
		<name>light</name>
		<pose>Unspecified</pose>
		<truncated>0</truncated>
		<difficult>0</difficult>
		<bndbox>
			<xmin>1397</xmin>
			<ymin>422</ymin>
			<xmax>1431</xmax>
			<ymax>434</ymax>
		</bndbox>
	</object>
	<object>
		<name>light</name>
		<pose>Unspecified</pose>
		<truncated>0</truncated>
		<difficult>0</difficult>
		<bndbox>
			<xmin>1357</xmin>
			<ymin>422</ymin>
			<xmax>1394</xmax>
			<ymax>434</ymax>
		</bndbox>
	</object>
	<object>
		<name>light</name>
		<pose>Unspecified</pose>
		<truncated>0</truncated>
		<difficult>0</difficult>
		<bndbox>
			<xmin>1319</xmin>
			<ymin>422</ymin>
			<xmax>1353</xmax>
			<ymax>435</ymax>
		</bndbox>
	</object>
	<object>
		<name>light</name>
		<pose>Unspecified</pose>
		<truncated>0</truncated>
		<difficult>0</difficult>
		<bndbox>
			<xmin>1282</xmin>
			<ymin>422</ymin>
			<xmax>1316</xmax>
			<ymax>435</ymax>
		</bndbox>
	</object>
	<object>
		<name>light</name>
		<pose>Unspecified</pose>
		<truncated>0</truncated>
		<difficult>0</difficult>
		<bndbox>
			<xmin>1245</xmin>
			<ymin>422</ymin>
			<xmax>1279</xmax>
			<ymax>434</ymax>
		</bndbox>
	</object>
	<object>
		<name>light</name>
		<pose>Unspecified</pose>
		<truncated>0</truncated>
		<difficult>0</difficult>
		<bndbox>
			<xmin>1202</xmin>
			<ymin>421</ymin>
			<xmax>1246</xmax>
			<ymax>437</ymax>
		</bndbox>
	</object>
	<object>
		<name>light</name>
		<pose>Unspecified</pose>
		<truncated>0</truncated>
		<difficult>0</difficult>
		<bndbox>
			<xmin>1165</xmin>
			<ymin>423</ymin>
			<xmax>1201</xmax>
			<ymax>436</ymax>
		</bndbox>
	</object>
	<object>
		<name>light</name>
		<pose>Unspecified</pose>
		<truncated>0</truncated>
		<difficult>0</difficult>
		<bndbox>
			<xmin>1128</xmin>
			<ymin>423</ymin>
			<xmax>1164</xmax>
			<ymax>436</ymax>
		</bndbox>
	</object>
	<object>
		<name>light</name>
		<pose>Unspecified</pose>
		<truncated>0</truncated>
		<difficult>0</difficult>
		<bndbox>
			<xmin>1091</xmin>
			<ymin>423</ymin>
			<xmax>1127</xmax>
			<ymax>436</ymax>
		</bndbox>
	</object>
	<object>
		<name>light</name>
		<pose>Unspecified</pose>
		<truncated>0</truncated>
		<difficult>0</difficult>
		<bndbox>
			<xmin>1050</xmin>
			<ymin>423</ymin>
			<xmax>1086</xmax>
			<ymax>436</ymax>
		</bndbox>
	</object>
	<object>
		<name>light</name>
		<pose>Unspecified</pose>
		<truncated>0</truncated>
		<difficult>0</difficult>
		<bndbox>
			<xmin>1015</xmin>
			<ymin>424</ymin>
			<xmax>1049</xmax>
			<ymax>436</ymax>
		</bndbox>
	</object>
	<object>
		<name>light</name>
		<pose>Unspecified</pose>
		<truncated>0</truncated>
		<difficult>0</difficult>
		<bndbox>
			<xmin>978</xmin>
			<ymin>424</ymin>
			<xmax>1011</xmax>
			<ymax>436</ymax>
		</bndbox>
	</object>
	<object>
		<name>light</name>
		<pose>Unspecified</pose>
		<truncated>0</truncated>
		<difficult>0</difficult>
		<bndbox>
			<xmin>937</xmin>
			<ymin>424</ymin>
			<xmax>979</xmax>
			<ymax>438</ymax>
		</bndbox>
	</object>
	<object>
		<name>light</name>
		<pose>Unspecified</pose>
		<truncated>0</truncated>
		<difficult>0</difficult>
		<bndbox>
			<xmin>902</xmin>
			<ymin>423</ymin>
			<xmax>937</xmax>
			<ymax>437</ymax>
		</bndbox>
	</object>
	<object>
		<name>light</name>
		<pose>Unspecified</pose>
		<truncated>0</truncated>
		<difficult>0</difficult>
		<bndbox>
			<xmin>864</xmin>
			<ymin>424</ymin>
			<xmax>900</xmax>
			<ymax>438</ymax>
		</bndbox>
	</object>
	<object>
		<name>light</name>
		<pose>Unspecified</pose>
		<truncated>0</truncated>
		<difficult>0</difficult>
		<bndbox>
			<xmin>825</xmin>
			<ymin>424</ymin>
			<xmax>860</xmax>
			<ymax>438</ymax>
		</bndbox>
	</object>
	<object>
		<name>light</name>
		<pose>Unspecified</pose>
		<truncated>0</truncated>
		<difficult>0</difficult>
		<bndbox>
			<xmin>789</xmin>
			<ymin>425</ymin>
			<xmax>824</xmax>
			<ymax>438</ymax>
		</bndbox>
	</object>
	<object>
		<name>light</name>
		<pose>Unspecified</pose>
		<truncated>0</truncated>
		<difficult>0</difficult>
		<bndbox>
			<xmin>749</xmin>
			<ymin>425</ymin>
			<xmax>784</xmax>
			<ymax>438</ymax>
		</bndbox>
	</object>
	<object>
		<name>light</name>
		<pose>Unspecified</pose>
		<truncated>0</truncated>
		<difficult>0</difficult>
		<bndbox>
			<xmin>710</xmin>
			<ymin>425</ymin>
			<xmax>747</xmax>
			<ymax>438</ymax>
		</bndbox>
	</object>
	<object>
		<name>light</name>
		<pose>Unspecified</pose>
		<truncated>0</truncated>
		<difficult>0</difficult>
		<bndbox>
			<xmin>673</xmin>
			<ymin>425</ymin>
			<xmax>707</xmax>
			<ymax>438</ymax>
		</bndbox>
	</object>
	<object>
		<name>light</name>
		<pose>Unspecified</pose>
		<truncated>0</truncated>
		<difficult>0</difficult>
		<bndbox>
			<xmin>633</xmin>
			<ymin>425</ymin>
			<xmax>677</xmax>
			<ymax>439</ymax>
		</bndbox>
	</object>
	<object>
		<name>light</name>
		<pose>Unspecified</pose>
		<truncated>0</truncated>
		<difficult>0</difficult>
		<bndbox>
			<xmin>597</xmin>
			<ymin>426</ymin>
			<xmax>634</xmax>
			<ymax>438</ymax>
		</bndbox>
	</object>
	<object>
		<name>light</name>
		<pose>Unspecified</pose>
		<truncated>0</truncated>
		<difficult>0</difficult>
		<bndbox>
			<xmin>561</xmin>
			<ymin>425</ymin>
			<xmax>595</xmax>
			<ymax>440</ymax>
		</bndbox>
	</object>
	<object>
		<name>light</name>
		<pose>Unspecified</pose>
		<truncated>0</truncated>
		<difficult>0</difficult>
		<bndbox>
			<xmin>522</xmin>
			<ymin>425</ymin>
			<xmax>556</xmax>
			<ymax>439</ymax>
		</bndbox>
	</object>
	<object>
		<name>light</name>
		<pose>Unspecified</pose>
		<truncated>0</truncated>
		<difficult>0</difficult>
		<bndbox>
			<xmin>485</xmin>
			<ymin>425</ymin>
			<xmax>517</xmax>
			<ymax>439</ymax>
		</bndbox>
	</object>
	<object>
		<name>light</name>
		<pose>Unspecified</pose>
		<truncated>0</truncated>
		<difficult>0</difficult>
		<bndbox>
			<xmin>448</xmin>
			<ymin>425</ymin>
			<xmax>482</xmax>
			<ymax>439</ymax>
		</bndbox>
	</object>
	<object>
		<name>light</name>
		<pose>Unspecified</pose>
		<truncated>0</truncated>
		<difficult>0</difficult>
		<bndbox>
			<xmin>407</xmin>
			<ymin>425</ymin>
			<xmax>441</xmax>
			<ymax>439</ymax>
		</bndbox>
	</object>
	<object>
		<name>light</name>
		<pose>Unspecified</pose>
		<truncated>0</truncated>
		<difficult>0</difficult>
		<bndbox>
			<xmin>368</xmin>
			<ymin>425</ymin>
			<xmax>409</xmax>
			<ymax>439</ymax>
		</bndbox>
	</object>
	<object>
		<name>light</name>
		<pose>Unspecified</pose>
		<truncated>0</truncated>
		<difficult>0</difficult>
		<bndbox>
			<xmin>330</xmin>
			<ymin>425</ymin>
			<xmax>367</xmax>
			<ymax>439</ymax>
		</bndbox>
	</object>
	<object>
		<name>light</name>
		<pose>Unspecified</pose>
		<truncated>0</truncated>
		<difficult>0</difficult>
		<bndbox>
			<xmin>294</xmin>
			<ymin>425</ymin>
			<xmax>326</xmax>
			<ymax>439</ymax>
		</bndbox>
	</object>
	<object>
		<name>light</name>
		<pose>Unspecified</pose>
		<truncated>0</truncated>
		<difficult>0</difficult>
		<bndbox>
			<xmin>253</xmin>
			<ymin>425</ymin>
			<xmax>288</xmax>
			<ymax>439</ymax>
		</bndbox>
	</object>
	<object>
		<name>light</name>
		<pose>Unspecified</pose>
		<truncated>0</truncated>
		<difficult>0</difficult>
		<bndbox>
			<xmin>216</xmin>
			<ymin>425</ymin>
			<xmax>250</xmax>
			<ymax>439</ymax>
		</bndbox>
	</object>
	<object>
		<name>light</name>
		<pose>Unspecified</pose>
		<truncated>0</truncated>
		<difficult>0</difficult>
		<bndbox>
			<xmin>175</xmin>
			<ymin>425</ymin>
			<xmax>211</xmax>
			<ymax>439</ymax>
		</bndbox>
	</object>
	<object>
		<name>light</name>
		<pose>Unspecified</pose>
		<truncated>0</truncated>
		<difficult>0</difficult>
		<bndbox>
			<xmin>136</xmin>
			<ymin>425</ymin>
			<xmax>172</xmax>
			<ymax>439</ymax>
		</bndbox>
	</object>
	<object>
		<name>light</name>
		<pose>Unspecified</pose>
		<truncated>1</truncated>
		<difficult>0</difficult>
		<bndbox>
			<xmin>114</xmin>
			<ymin>425</ymin>
			<xmax>135</xmax>
			<ymax>437</ymax>
		</bndbox>
	</object>
</annotation>