<annotation>
	<folder>&#26631;&#27880;&#20869;&#23481;</folder>
	<filename>K387+501_K387+531_17.jpg</filename>
	<path>./enhance_xml/K387+501_K387+531_17.jpg</path>
	<source>
		<database>Unknown</database>
	</source>
	<size>
		<width>1628</width>
		<height>635</height>
		<depth>1</depth>
	</size>
	<segmented>0</segmented>
	<object>
		<name>light</name>
		<pose>Unspecified</pose>
		<truncated>0</truncated>
		<difficult>0</difficult>
		<bndbox>
			<xmin>1398</xmin>
			<ymin>199</ymin>
			<xmax>1439</xmax>
			<ymax>215</ymax>
		</bndbox>
	</object>
	<object>
		<name>light</name>
		<pose>Unspecified</pose>
		<truncated>0</truncated>
		<difficult>0</difficult>
		<bndbox>
			<xmin>820</xmin>
			<ymin>200</ymin>
			<xmax>861</xmax>
			<ymax>216</ymax>
		</bndbox>
	</object>
	<object>
		<name>light</name>
		<pose>Unspecified</pose>
		<truncated>0</truncated>
		<difficult>0</difficult>
		<bndbox>
			<xmin>1105</xmin>
			<ymin>202</ymin>
			<xmax>1134</xmax>
			<ymax>211</ymax>
		</bndbox>
	</object>
	<object>
		<name>light</name>
		<pose>Unspecified</pose>
		<truncated>0</truncated>
		<difficult>0</difficult>
		<bndbox>
			<xmin>1303</xmin>
			<ymin>427</ymin>
			<xmax>1349</xmax>
			<ymax>445</ymax>
		</bndbox>
	</object>
	<object>
		<name>light</name>
		<pose>Unspecified</pose>
		<truncated>0</truncated>
		<difficult>0</difficult>
		<bndbox>
			<xmin>1035</xmin>
			<ymin>429</ymin>
			<xmax>1081</xmax>
			<ymax>446</ymax>
		</bndbox>
	</object>
	<object>
		<name>light</name>
		<pose>Unspecified</pose>
		<truncated>0</truncated>
		<difficult>0</difficult>
		<bndbox>
			<xmin>762</xmin>
			<ymin>427</ymin>
			<xmax>809</xmax>
			<ymax>445</ymax>
		</bndbox>
	</object>
	<object>
		<name>light</name>
		<pose>Unspecified</pose>
		<truncated>0</truncated>
		<difficult>0</difficult>
		<bndbox>
			<xmin>491</xmin>
			<ymin>430</ymin>
			<xmax>537</xmax>
			<ymax>447</ymax>
		</bndbox>
	</object>
	<object>
		<name>light</name>
		<pose>Unspecified</pose>
		<truncated>0</truncated>
		<difficult>0</difficult>
		<bndbox>
			<xmin>267</xmin>
			<ymin>202</ymin>
			<xmax>311</xmax>
			<ymax>218</ymax>
		</bndbox>
	</object>
	<object>
		<name>light</name>
		<pose>Unspecified</pose>
		<truncated>0</truncated>
		<difficult>0</difficult>
		<bndbox>
			<xmin>223</xmin>
			<ymin>430</ymin>
			<xmax>266</xmax>
			<ymax>446</ymax>
		</bndbox>
	</object>
	<object>
		<name>light</name>
		<pose>Unspecified</pose>
		<truncated>0</truncated>
		<difficult>0</difficult>
		<bndbox>
			<xmin>543</xmin>
			<ymin>203</ymin>
			<xmax>572</xmax>
			<ymax>212</ymax>
		</bndbox>
	</object>
</annotation>