<annotation>
	<folder>train</folder>
	<filename>K956+966_K957+16_38.jpg</filename>
	<path>./enhance_xml/K956+966_K957+16_38.jpg</path>
	<source>
		<database>Unknown</database>
	</source>
	<size>
		<width>1629</width>
		<height>384</height>
		<depth>3</depth>
	</size>
	<segmented>0</segmented>
	<object>
		<name>light</name>
		<pose>Unspecified</pose>
		<truncated>0</truncated>
		<difficult>0</difficult>
		<bndbox>
			<xmin>1599</xmin>
			<ymin>98</ymin>
			<xmax>1618</xmax>
			<ymax>110</ymax>
		</bndbox>
	</object>
	<object>
		<name>light</name>
		<pose>Unspecified</pose>
		<truncated>0</truncated>
		<difficult>0</difficult>
		<bndbox>
			<xmin>1597</xmin>
			<ymin>271</ymin>
			<xmax>1617</xmax>
			<ymax>286</ymax>
		</bndbox>
	</object>
	<object>
		<name>light</name>
		<pose>Unspecified</pose>
		<truncated>0</truncated>
		<difficult>0</difficult>
		<bndbox>
			<xmin>1493</xmin>
			<ymin>271</ymin>
			<xmax>1511</xmax>
			<ymax>286</ymax>
		</bndbox>
	</object>
	<object>
		<name>light</name>
		<pose>Unspecified</pose>
		<truncated>0</truncated>
		<difficult>0</difficult>
		<bndbox>
			<xmin>1385</xmin>
			<ymin>272</ymin>
			<xmax>1406</xmax>
			<ymax>287</ymax>
		</bndbox>
	</object>
	<object>
		<name>light</name>
		<pose>Unspecified</pose>
		<truncated>0</truncated>
		<difficult>0</difficult>
		<bndbox>
			<xmin>1396</xmin>
			<ymin>97</ymin>
			<xmax>1416</xmax>
			<ymax>109</ymax>
		</bndbox>
	</object>
	<object>
		<name>light</name>
		<pose>Unspecified</pose>
		<truncated>0</truncated>
		<difficult>0</difficult>
		<bndbox>
			<xmin>1497</xmin>
			<ymin>98</ymin>
			<xmax>1518</xmax>
			<ymax>109</ymax>
		</bndbox>
	</object>
	<object>
		<name>light</name>
		<pose>Unspecified</pose>
		<truncated>0</truncated>
		<difficult>0</difficult>
		<bndbox>
			<xmin>1288</xmin>
			<ymin>272</ymin>
			<xmax>1307</xmax>
			<ymax>285</ymax>
		</bndbox>
	</object>
	<object>
		<name>light</name>
		<pose>Unspecified</pose>
		<truncated>0</truncated>
		<difficult>0</difficult>
		<bndbox>
			<xmin>1180</xmin>
			<ymin>272</ymin>
			<xmax>1202</xmax>
			<ymax>286</ymax>
		</bndbox>
	</object>
	<object>
		<name>light</name>
		<pose>Unspecified</pose>
		<truncated>0</truncated>
		<difficult>0</difficult>
		<bndbox>
			<xmin>1085</xmin>
			<ymin>275</ymin>
			<xmax>1103</xmax>
			<ymax>287</ymax>
		</bndbox>
	</object>
	<object>
		<name>light</name>
		<pose>Unspecified</pose>
		<truncated>0</truncated>
		<difficult>0</difficult>
		<bndbox>
			<xmin>1084</xmin>
			<ymin>95</ymin>
			<xmax>1105</xmax>
			<ymax>109</ymax>
		</bndbox>
	</object>
	<object>
		<name>light</name>
		<pose>Unspecified</pose>
		<truncated>0</truncated>
		<difficult>0</difficult>
		<bndbox>
			<xmin>1187</xmin>
			<ymin>95</ymin>
			<xmax>1206</xmax>
			<ymax>109</ymax>
		</bndbox>
	</object>
	<object>
		<name>light</name>
		<pose>Unspecified</pose>
		<truncated>0</truncated>
		<difficult>0</difficult>
		<bndbox>
			<xmin>1293</xmin>
			<ymin>96</ymin>
			<xmax>1312</xmax>
			<ymax>110</ymax>
		</bndbox>
	</object>
	<object>
		<name>light</name>
		<pose>Unspecified</pose>
		<truncated>0</truncated>
		<difficult>0</difficult>
		<bndbox>
			<xmin>980</xmin>
			<ymin>95</ymin>
			<xmax>1000</xmax>
			<ymax>109</ymax>
		</bndbox>
	</object>
	<object>
		<name>light</name>
		<pose>Unspecified</pose>
		<truncated>0</truncated>
		<difficult>0</difficult>
		<bndbox>
			<xmin>879</xmin>
			<ymin>94</ymin>
			<xmax>898</xmax>
			<ymax>109</ymax>
		</bndbox>
	</object>
	<object>
		<name>light</name>
		<pose>Unspecified</pose>
		<truncated>0</truncated>
		<difficult>0</difficult>
		<bndbox>
			<xmin>982</xmin>
			<ymin>273</ymin>
			<xmax>1003</xmax>
			<ymax>287</ymax>
		</bndbox>
	</object>
	<object>
		<name>light</name>
		<pose>Unspecified</pose>
		<truncated>0</truncated>
		<difficult>0</difficult>
		<bndbox>
			<xmin>879</xmin>
			<ymin>272</ymin>
			<xmax>901</xmax>
			<ymax>287</ymax>
		</bndbox>
	</object>
	<object>
		<name>light</name>
		<pose>Unspecified</pose>
		<truncated>0</truncated>
		<difficult>0</difficult>
		<bndbox>
			<xmin>781</xmin>
			<ymin>275</ymin>
			<xmax>802</xmax>
			<ymax>287</ymax>
		</bndbox>
	</object>
	<object>
		<name>light</name>
		<pose>Unspecified</pose>
		<truncated>0</truncated>
		<difficult>0</difficult>
		<bndbox>
			<xmin>777</xmin>
			<ymin>95</ymin>
			<xmax>803</xmax>
			<ymax>109</ymax>
		</bndbox>
	</object>
	<object>
		<name>light</name>
		<pose>Unspecified</pose>
		<truncated>0</truncated>
		<difficult>0</difficult>
		<bndbox>
			<xmin>682</xmin>
			<ymin>275</ymin>
			<xmax>698</xmax>
			<ymax>287</ymax>
		</bndbox>
	</object>
	<object>
		<name>light</name>
		<pose>Unspecified</pose>
		<truncated>0</truncated>
		<difficult>0</difficult>
		<bndbox>
			<xmin>632</xmin>
			<ymin>275</ymin>
			<xmax>649</xmax>
			<ymax>287</ymax>
		</bndbox>
	</object>
	<object>
		<name>light</name>
		<pose>Unspecified</pose>
		<truncated>0</truncated>
		<difficult>0</difficult>
		<bndbox>
			<xmin>570</xmin>
			<ymin>274</ymin>
			<xmax>586</xmax>
			<ymax>287</ymax>
		</bndbox>
	</object>
	<object>
		<name>light</name>
		<pose>Unspecified</pose>
		<truncated>0</truncated>
		<difficult>0</difficult>
		<bndbox>
			<xmin>679</xmin>
			<ymin>95</ymin>
			<xmax>697</xmax>
			<ymax>106</ymax>
		</bndbox>
	</object>
	<object>
		<name>light</name>
		<pose>Unspecified</pose>
		<truncated>0</truncated>
		<difficult>0</difficult>
		<bndbox>
			<xmin>634</xmin>
			<ymin>96</ymin>
			<xmax>652</xmax>
			<ymax>108</ymax>
		</bndbox>
	</object>
	<object>
		<name>light</name>
		<pose>Unspecified</pose>
		<truncated>0</truncated>
		<difficult>0</difficult>
		<bndbox>
			<xmin>578</xmin>
			<ymin>95</ymin>
			<xmax>595</xmax>
			<ymax>108</ymax>
		</bndbox>
	</object>
	<object>
		<name>light</name>
		<pose>Unspecified</pose>
		<truncated>0</truncated>
		<difficult>0</difficult>
		<bndbox>
			<xmin>511</xmin>
			<ymin>275</ymin>
			<xmax>530</xmax>
			<ymax>286</ymax>
		</bndbox>
	</object>
	<object>
		<name>light</name>
		<pose>Unspecified</pose>
		<truncated>0</truncated>
		<difficult>0</difficult>
		<bndbox>
			<xmin>452</xmin>
			<ymin>273</ymin>
			<xmax>472</xmax>
			<ymax>287</ymax>
		</bndbox>
	</object>
	<object>
		<name>light</name>
		<pose>Unspecified</pose>
		<truncated>0</truncated>
		<difficult>0</difficult>
		<bndbox>
			<xmin>395</xmin>
			<ymin>275</ymin>
			<xmax>412</xmax>
			<ymax>287</ymax>
		</bndbox>
	</object>
	<object>
		<name>light</name>
		<pose>Unspecified</pose>
		<truncated>0</truncated>
		<difficult>0</difficult>
		<bndbox>
			<xmin>329</xmin>
			<ymin>275</ymin>
			<xmax>344</xmax>
			<ymax>286</ymax>
		</bndbox>
	</object>
	<object>
		<name>light</name>
		<pose>Unspecified</pose>
		<truncated>0</truncated>
		<difficult>0</difficult>
		<bndbox>
			<xmin>264</xmin>
			<ymin>273</ymin>
			<xmax>282</xmax>
			<ymax>286</ymax>
		</bndbox>
	</object>
	<object>
		<name>light</name>
		<pose>Unspecified</pose>
		<truncated>0</truncated>
		<difficult>0</difficult>
		<bndbox>
			<xmin>204</xmin>
			<ymin>274</ymin>
			<xmax>221</xmax>
			<ymax>286</ymax>
		</bndbox>
	</object>
	<object>
		<name>light</name>
		<pose>Unspecified</pose>
		<truncated>0</truncated>
		<difficult>0</difficult>
		<bndbox>
			<xmin>145</xmin>
			<ymin>275</ymin>
			<xmax>160</xmax>
			<ymax>287</ymax>
		</bndbox>
	</object>
	<object>
		<name>light</name>
		<pose>Unspecified</pose>
		<truncated>0</truncated>
		<difficult>0</difficult>
		<bndbox>
			<xmin>82</xmin>
			<ymin>272</ymin>
			<xmax>99</xmax>
			<ymax>287</ymax>
		</bndbox>
	</object>
	<object>
		<name>light</name>
		<pose>Unspecified</pose>
		<truncated>0</truncated>
		<difficult>0</difficult>
		<bndbox>
			<xmin>30</xmin>
			<ymin>273</ymin>
			<xmax>46</xmax>
			<ymax>290</ymax>
		</bndbox>
	</object>
	<object>
		<name>light</name>
		<pose>Unspecified</pose>
		<truncated>0</truncated>
		<difficult>0</difficult>
		<bndbox>
			<xmin>30</xmin>
			<ymin>95</ymin>
			<xmax>47</xmax>
			<ymax>108</ymax>
		</bndbox>
	</object>
	<object>
		<name>light</name>
		<pose>Unspecified</pose>
		<truncated>0</truncated>
		<difficult>0</difficult>
		<bndbox>
			<xmin>89</xmin>
			<ymin>94</ymin>
			<xmax>107</xmax>
			<ymax>108</ymax>
		</bndbox>
	</object>
	<object>
		<name>light</name>
		<pose>Unspecified</pose>
		<truncated>0</truncated>
		<difficult>0</difficult>
		<bndbox>
			<xmin>151</xmin>
			<ymin>95</ymin>
			<xmax>171</xmax>
			<ymax>107</ymax>
		</bndbox>
	</object>
	<object>
		<name>light</name>
		<pose>Unspecified</pose>
		<truncated>0</truncated>
		<difficult>0</difficult>
		<bndbox>
			<xmin>210</xmin>
			<ymin>95</ymin>
			<xmax>228</xmax>
			<ymax>108</ymax>
		</bndbox>
	</object>
	<object>
		<name>light</name>
		<pose>Unspecified</pose>
		<truncated>0</truncated>
		<difficult>0</difficult>
		<bndbox>
			<xmin>276</xmin>
			<ymin>96</ymin>
			<xmax>291</xmax>
			<ymax>108</ymax>
		</bndbox>
	</object>
	<object>
		<name>light</name>
		<pose>Unspecified</pose>
		<truncated>0</truncated>
		<difficult>0</difficult>
		<bndbox>
			<xmin>328</xmin>
			<ymin>94</ymin>
			<xmax>345</xmax>
			<ymax>106</ymax>
		</bndbox>
	</object>
	<object>
		<name>light</name>
		<pose>Unspecified</pose>
		<truncated>0</truncated>
		<difficult>0</difficult>
		<bndbox>
			<xmin>395</xmin>
			<ymin>95</ymin>
			<xmax>415</xmax>
			<ymax>108</ymax>
		</bndbox>
	</object>
	<object>
		<name>light</name>
		<pose>Unspecified</pose>
		<truncated>0</truncated>
		<difficult>0</difficult>
		<bndbox>
			<xmin>460</xmin>
			<ymin>96</ymin>
			<xmax>477</xmax>
			<ymax>108</ymax>
		</bndbox>
	</object>
	<object>
		<name>light</name>
		<pose>Unspecified</pose>
		<truncated>0</truncated>
		<difficult>0</difficult>
		<bndbox>
			<xmin>521</xmin>
			<ymin>95</ymin>
			<xmax>540</xmax>
			<ymax>108</ymax>
		</bndbox>
	</object>
</annotation>